HISTORY.md
LICENSE
MANIFEST.in
README.md
setup.cfg
setup.py
docs/Makefile
docs/conf.py
docs/index.rst
docs/installation.rst
docs/make.bat
docs/readme.rst
docs/usage.rst
docs/images/architecture.png
docs/images/clinical_annotation.png
docs/images/cpat_icon.png
docs/images/cpat_logo.png
docs/images/cpat_report.png
docs/images/panno_icon.png
docs/images/panno_icon_lowres.png
docs/images/panno_logo.png
docs/images/panno_logo_lowres.png
docs/images/panno_report.png
panno/.DS_Store
panno/__init__.py
panno/clinical_annotation.py
panno/genotype_resolution.py
panno/panno.py
panno/pgx_report.py
panno/predict_diplotype.py
panno/test.py
panno.egg-info/PKG-INFO
panno.egg-info/SOURCES.txt
panno.egg-info/dependency_links.txt
panno.egg-info/entry_points.txt
panno.egg-info/not-zip-safe
panno.egg-info/requires.txt
panno.egg-info/top_level.txt
panno/assets/.DS_Store
panno/assets/bootstrap.min.css
panno/assets/custom.css
panno/assets/jquery.toast.css
panno/assets/panno_icon.png
panno/assets/panno_logo.png
panno/assets/pgx_diplotypes.json
panno/assets/pgx_kb.sqlite3
panno/assets/pgx_loci.bed
tests/__init__.py
tests/test_panno.py