Metadata-Version: 2.1
Name: panno
Version: 0.3.0
Summary: PAnno is a Pharmacogenomics Annotation tool for clinical genomic testing.
Home-page: https://github.com/PreMedKB/PAnno
Author: Yaqing Liu
Author-email: yaqing.liu@outlook.com
Keywords: pharmacogenomics,pharmacology,drug responses,genomics,bioinformatics
Classifier: Development Status :: 2 - Pre-Alpha
Classifier: Environment :: Console
Classifier: Environment :: Web Environment
Classifier: Intended Audience :: Science/Research
Classifier: License :: OSI Approved :: Mozilla Public License 2.0 (MPL 2.0)
Classifier: Natural Language :: English
Classifier: Operating System :: MacOS :: MacOS X
Classifier: Operating System :: POSIX
Classifier: Operating System :: Unix
Classifier: Programming Language :: Python :: 3
Classifier: Programming Language :: Python :: 3.7
Classifier: Programming Language :: Python :: 3.8
Classifier: Programming Language :: Python :: 3.9
Classifier: Programming Language :: Python :: 3.10
Requires-Python: >=3.7
License-File: LICENSE
